gdcr_client.py
gdcr_client-0.9.3.dist-info/METADATA
gdcr_client-0.9.3.dist-info/RECORD
gdcr_client-0.9.3.dist-info/WHEEL
gdcr_client-0.9.3.dist-info/top_level.txt
